{"tags":[{"title":"linkedin","color":"#61DD61","textcolor":"white","type":"sidecar"},{"title":"rrss","color":"#61DD61","textcolor":"white","type":"sidecar"},{"title":"svg","color":"#61DD61","textcolor":"white","type":"sidecar"},{"title":"goitikbehera","color":"#61DD61","textcolor":"white","type":"sidecar"},{"title":"bideojokoa","color":"#61DD61","textcolor":"white","type":"sidecar"},{"title":"ikonoa","color":"#61DD61","textcolor":"white","type":"sidecar"},{"title":"saresozialak","color":"#61DD61","textcolor":"white","type":"sidecar"},{"title":"bektoriala","color":"#61DD61","textcolor":"white","type":"sidecar"},{"title":"irudia","color":"#61DD61","textcolor":"white","type":"sidecar"},{"title":"redessociales","color":"#4986e7ff","textcolor":"white","type":"sidecar"},{"title":"videojuego","color":"#4986e7ff","textcolor":"white","type":"sidecar"},{"title":"videogame","color":"#c2c2c2ff","textcolor":"white","type":"sidecar"},{"title":"socialmedia","color":"#c2c2c2ff","textcolor":"white","type":"sidecar"},{"title":"icono","color":"#4986e7ff","textcolor":"white","type":"sidecar"},{"title":"icon","color":"#c2c2c2ff","textcolor":"white","type":"sidecar"},{"title":"imagen","color":"#4986e7ff","textcolor":"white","type":"sidecar"},{"title":"image","color":"#c2c2c2ff","textcolor":"white","type":"sidecar"},{"title":"egina","color":"#61DD61","textcolor":"white","type":"sidecar"},{"title":"realizado","color":"#4986e7ff","textcolor":"white","type":"sidecar"},{"title":"finish","color":"#c2c2c2ff","textcolor":"white","type":"sidecar"},{"title":"vectorial","color":"#4986e7ff","textcolor":"white","type":"sidecar"}],"appName":"TagSpaces","appVersion":"5.1.1","lastUpdated":"2023-01-09T17:20:06.008Z"}